Vectors/replication-operator/replication_operator.v
module replication_operator (
    input [7:0] in,
    output [31:0] out );
    wire [23:0]temp;
    
    assign temp = {24{in[7]}};
    assign out = {temp[23:0], in[7:0]};

endmodule

module testbench;
    
    // Inputs
    reg [7:0] in;

    // Outputs
    wire [31:0] out;
    
    // Instantiate the module
    replication_operator dut (
    .in(in),
    .out(out)
    );
    
    initial begin
        $dumpfile("replication_operator.vcd");
        $dumpvars(0, testbench);
    end

    initial begin

        $display("Generating 8 random inputs");
        // Generate 8 random inputs and print the inputs and outputs
        for (integer i = 0; i < 8; i++) begin
            in = $random;
            #1;  // Wait 1 time unit
            $display("Input = %h", in);
            $display("Output");
            $display("Output = %h", out);
            $display("\n");
        end
        
        $finish;  // End the simulation
    end
    
endmodule

Vectors/replication-operator/replication_operator.vcd
$date
	Tue Jan  3 18:31:27 2023
$end
$version
	Icarus Verilog
$end
$timescale
	1s
$end
$scope module testbench $end
$var wire 32 ! out [31:0] $end
$var reg 8 " in [7:0] $end
$scope module dut $end
$var wire 8 # in [7:0] $end
$var wire 24 $ temp [23:0] $end
$var wire 32 % out [31:0] $end
$upscope $end
$scope begin $ivl_for_loop0 $end
$var integer 32 & i [31:0] $end
$upscope $end
$upscope $end
$enddefinitions $end
#0
$dumpvars
b0 &
b100100 %
b0 $
b100100 #
b100100 "
b100100 !
$end
#1
b111111111111111111111111 $
b11111111111111111111111110000001 !
b11111111111111111111111110000001 %
b10000001 "
b10000001 #
b1 &
#2
b0 $
b1001 !
b1001 %
b1001 "
b1001 #
b10 &
#3
b1100011 !
b1100011 %
b1100011 "
b1100011 #
b11 &
#4
b1101 !
b1101 %
b1101 "
b1101 #
b100 &
#5
b111111111111111111111111 $
b11111111111111111111111110001101 !
b11111111111111111111111110001101 %
b10001101 "
b10001101 #
b101 &
#6
b0 $
b1100101 !
b1100101 %
b1100101 "
b1100101 #
b110 &
#7
b10010 !
b10010 %
b10010 "
b10010 #
b111 &
#8
b1000 &
