Vectors/vector-reversal/vector_reversal.v
module vector_reversal ( 
    input [7:0] in,
    output [7:0] out
);
    assign out = {in[0],in[1],in[2],in[3],in[4],in[5],in[6],in[7]};

endmodule

module testbench;
    
    // Inputs
    reg [7:0] in;

    // Outputs
    wire [7:0] out;
    
    // Instantiate the module
    vector_reversal dut (
    .in(in),
    .out(out)
    );
    
    initial begin
        $dumpfile("vector_reversal.vcd");
        $dumpvars(0, testbench);
    end

    initial begin

        $display("Generating 8 random inputs");
        // Generate 8 random inputs and print the inputs and outputs
        for (integer i = 0; i < 8; i++) begin
            in = $random;
            #1;  // Wait 1 time unit
            $display("Input = %b", in);
            $display("Output");
            $display("Output = %b", out);
            $display("\n");
        end
        
        $finish;  // End the simulation
    end
    
endmodule

Vectors/vector-reversal/vector_reversal.vcd
$date
	Tue Jan  3 13:21:12 2023
$end
$version
	Icarus Verilog
$end
$timescale
	1s
$end
$scope module testbench $end
$var wire 8 ! out [7:0] $end
$var reg 8 " in [7:0] $end
$scope module dut $end
$var wire 8 # in [7:0] $end
$var wire 8 $ out [7:0] $end
$upscope $end
$scope begin $ivl_for_loop0 $end
$var integer 32 % i [31:0] $end
$upscope $end
$upscope $end
$enddefinitions $end
#0
$dumpvars
b0 %
b10000 $
b1000 #
b1000 "
b10000 !
$end
#1
b1 %
#2
b10 %
#3
b11 %
#4
b100 %
#5
b101 %
#6
b110 %
#7
b111 %
#8
b1000 %
