Vectors/bitwise-logical-operators/bitwise_logical_operator.v
module bitwise_logical_operators( 
    input [2:0] a,
    input [2:0] b,
    output [2:0] out_or_bitwise,
    output out_or_logical,
    output [5:0] out_not
);

        assign out_or_bitwise = a | b;
        assign out_or_logical = a || b; 
        assign out_not[5:3] = ~b;
        assign out_not[2:0] = ~a;

endmodule

module testbench;
    
    // Inputs
    reg [2:0] a;
    reg [2:0] b; 

    // Outputs
    wire [2:0] out_or_bitwise;
    wire out_or_logical;
    wire [5:0] out_not;
    
    // Instantiate the module
    bitwise_logical_operators dut (
        .a(a),
        .b(b),
        .out_or_bitwise(out_or_bitwise),
        .out_or_logical(out_or_logical),
        .out_not(out_not)
    );
    
    initial begin
        $dumpfile("bitwise_logical_operators.vcd");
        $dumpvars(0, testbench);
    end

    initial begin

        $display("Generating 8 random inputs");
        // Generate 8 random inputs and print the inputs and outputs
        for (integer i = 0; i < 8; i++) begin
            a = $random;
            b = 0; 
            #1;  // Wait 1 time unit
            $display("Input a = %h", a);
            $display("Input b = %h", b);
            $display("Output_or_bitwise = %h", out_or_bitwise);
            $display("Output_or_logical = %h", out_or_logical);
            $display("Output_not = %h", out_not);
            $display("\n");
        end
        
        $finish;  // End the simulation
    end
    
endmodule

Vectors/bitwise-logical-operators/bitwise_logical_operators.vcd
$date
	Mon Jan  2 13:25:16 2023
$end
$version
	Icarus Verilog
$end
$timescale
	1s
$end
$scope module testbench $end
$var wire 1 ! out_or_logical $end
$var wire 3 " out_or_bitwise [2:0] $end
$var wire 6 # out_not [5:0] $end
$var reg 3 $ a [2:0] $end
$var reg 3 % b [2:0] $end
$scope module dut $end
$var wire 3 & a [2:0] $end
$var wire 3 ' b [2:0] $end
$var wire 3 ( out_or_bitwise [2:0] $end
$var wire 1 ! out_or_logical $end
$var wire 6 ) out_not [5:0] $end
$upscope $end
$scope begin $ivl_for_loop0 $end
$var integer 32 * i [31:0] $end
$upscope $end
$upscope $end
$enddefinitions $end
#0
$dumpvars
b0 *
b111011 )
b100 (
b0 '
b100 &
b0 %
b100 $
b111011 #
b100 "
1!
$end
#1
b1 "
b1 (
b111110 #
b111110 )
b1 $
b1 &
b1 *
#2
b10 *
#3
b11 "
b11 (
b111100 #
b111100 )
b11 $
b11 &
b11 *
#4
b101 "
b101 (
b111010 #
b111010 )
b101 $
b101 &
b100 *
#5
b101 *
#6
b110 *
#7
b10 "
b10 (
b111101 #
b111101 )
b10 $
b10 &
b111 *
#8
b1000 *
