7458-Chip/7458-chip.v
`timescale 1ns / 1ps

module chip_7458 ( 
    input p1a, p1b, p1c, p1d, p1e, p1f,
    output p1y,
    input p2a, p2b, p2c, p2d,
    output p2y );

    wire and_one; 
    wire and_two; 
    wire and_three; 
    wire and_four; 
    wire or_one; 
    wire or_two; 

    assign and_one = p2a & p2b; 
    assign and_two = p2c & p2d; 
    assign p2y = and_one | and_two; 

    assign and_three = p1a & p1c & p1b; 
    assign and_four = p1f & p1e & p1d; 
    assign p1y = and_three | and_four; 

endmodule



module testbench();
reg p1a, p1b, p1c, p1d, p1e, p1f;
wire p1y;
reg p2a, p2b, p2c, p2d;
wire p2y;
integer i; 

chip_7458 dut (
.p1a(p1a), .p1b(p1b), .p1c(p1c), .p1d(p1d), .p1e(p1e), .p1f(p1f),
.p1y(p1y),
.p2a(p2a), .p2b(p2b), .p2c(p2c), .p2d(p2d),
.p2y(p2y)
);

initial begin
  $dumpfile("7458_chip.vcd");
  $dumpvars(0, testbench);
end

initial begin
for (i = 0; i < 64; i = i +1) begin
// Set inputs
p1a = i[0]; p1b = i[1]; p1c = i[2]; p1d = i[3]; p1e = i[4]; p1f = i[5];
p2a = i[6]; p2b = i[7]; p2c = i[8]; p2d = i[9];
#1;
$display("Input = %b %b %b %b %b %b %b %b %b %b", p1a, p1b, p1c, p1d, p1e, p1f, p2a, p2b, p2c, p2d);
$display("Output = %b %b", p1y, p2y);
end
end
endmodule

7458-Chip/7458_chip.vcd
$date
	Sat Dec 31 22:55:18 2022
$end
$version
	Icarus Verilog
$end
$timescale
	1ps
$end
$scope module testbench $end
$var wire 1 ! p2y $end
$var wire 1 " p1y $end
$var reg 1 # p1a $end
$var reg 1 $ p1b $end
$var reg 1 % p1c $end
$var reg 1 & p1d $end
$var reg 1 ' p1e $end
$var reg 1 ( p1f $end
$var reg 1 ) p2a $end
$var reg 1 * p2b $end
$var reg 1 + p2c $end
$var reg 1 , p2d $end
$var integer 32 - i [31:0] $end
$scope module dut $end
$var wire 1 . and_four $end
$var wire 1 / and_one $end
$var wire 1 0 and_three $end
$var wire 1 1 and_two $end
$var wire 1 # p1a $end
$var wire 1 $ p1b $end
$var wire 1 % p1c $end
$var wire 1 & p1d $end
$var wire 1 ' p1e $end
$var wire 1 ( p1f $end
$var wire 1 " p1y $end
$var wire 1 ) p2a $end
$var wire 1 * p2b $end
$var wire 1 + p2c $end
$var wire 1 , p2d $end
$var wire 1 ! p2y $end
$upscope $end
$upscope $end
$enddefinitions $end
#0
$dumpvars
01
00
0/
0.
b0 -
0,
0+
0*
0)
0(
0'
0&
0%
0$
0#
0"
0!
$end
#1000
1#
b1 -
#2000
1$
0#
b10 -
#3000
1#
b11 -
#4000
1%
0$
0#
b100 -
#5000
1#
b101 -
#6000
1$
0#
b110 -
#7000
1"
10
1#
b111 -
#8000
0"
00
1&
0%
0$
0#
b1000 -
#9000
1#
b1001 -
#10000
1$
0#
b1010 -
#11000
1#
b1011 -
#12000
1%
0$
0#
b1100 -
#13000
1#
b1101 -
#14000
1$
0#
b1110 -
#15000
1"
10
1#
b1111 -
#16000
0"
00
1'
0&
0%
0$
0#
b10000 -
#17000
1#
b10001 -
#18000
1$
0#
b10010 -
#19000
1#
b10011 -
#20000
1%
0$
0#
b10100 -
#21000
1#
b10101 -
#22000
1$
0#
b10110 -
#23000
1"
10
1#
b10111 -
#24000
0"
00
1&
0%
0$
0#
b11000 -
#25000
1#
b11001 -
#26000
1$
0#
b11010 -
#27000
1#
b11011 -
#28000
1%
0$
0#
b11100 -
#29000
1#
b11101 -
#30000
1$
0#
b11110 -
#31000
1"
10
1#
b11111 -
#32000
0"
00
1(
0'
0&
0%
0$
0#
b100000 -
#33000
1#
b100001 -
#34000
1$
0#
b100010 -
#35000
1#
b100011 -
#36000
1%
0$
0#
b100100 -
#37000
1#
b100101 -
#38000
1$
0#
b100110 -
#39000
1"
10
1#
b100111 -
#40000
0"
00
1&
0%
0$
0#
b101000 -
#41000
1#
b101001 -
#42000
1$
0#
b101010 -
#43000
1#
b101011 -
#44000
1%
0$
0#
b101100 -
#45000
1#
b101101 -
#46000
1$
0#
b101110 -
#47000
1"
10
1#
b101111 -
#48000
0"
00
1'
0&
0%
0$
0#
b110000 -
#49000
1#
b110001 -
#50000
1$
0#
b110010 -
#51000
1#
b110011 -
#52000
1%
0$
0#
b110100 -
#53000
1#
b110101 -
#54000
1$
0#
b110110 -
#55000
1"
10
1#
b110111 -
#56000
1.
00
1&
0%
0$
0#
b111000 -
#57000
1#
b111001 -
#58000
1$
0#
b111010 -
#59000
1#
b111011 -
#60000
1%
0$
0#
b111100 -
#61000
1#
b111101 -
#62000
1$
0#
b111110 -
#63000
10
1#
b111111 -
#64000
b1000000 -
